python_wrap/__init__.py
python_wrap/decorators.py
python_wrap-0.1.0.dist-info/LICENSE
python_wrap-0.1.0.dist-info/METADATA
python_wrap-0.1.0.dist-info/WHEEL
python_wrap-0.1.0.dist-info/RECORD
