Metadata-Version: 2.1
Name: python-wrap
Version: 0.1.0
Summary: A comprehensive collection of Python decorators and utility functions for enhanced development workflows
Home-page: https://github.com/Pythondeveloper6/PythonWrap
License: MIT
Keywords: decorators,utilities,python,development,tools,python
Author: Mahmoud Ahmed
Author-email: contact.mahmoudahmed@gmail.com
Maintainer: Mahmoud Ahmed
Maintainer-email: contact.mahmoudahmed@gmail.com
Requires-Python: >=3.8,<4.0
Classifier: Development Status :: 4 - Beta
Classifier: Intended Audience :: Developers
Classifier: License :: OSI Approved :: MIT License
Classifier: Operating System :: OS Independent
Classifier: Programming Language :: Python :: 3
Classifier: Programming Language :: Python :: 3.8
Classifier: Programming Language :: Python :: 3.9
Classifier: Programming Language :: Python :: 3.10
Classifier: Programming Language :: Python :: 3.11
Classifier: Programming Language :: Python :: 3.12
Classifier: Programming Language :: Python :: 3.13
Classifier: Topic :: Software Development :: Libraries :: Application Frameworks
Classifier: Topic :: Software Development :: Libraries :: Python Modules
Classifier: Typing :: Typed
Requires-Dist: typing-extensions (>=4.7.1,<5.0.0)
Requires-Dist: wrapt (>=1.15.0,<2.0.0)
Project-URL: Bug Tracker, https://github.com/Pythondeveloper6/PythonWrap/issues
Project-URL: Changelog, https://github.com/Pythondeveloper6/PythonWrap/blob/main/CHANGELOG.md
Project-URL: Documentation, https://python-wrap.readthedocs.io
Project-URL: Repository, https://github.com/Pythondeveloper6/PythonWrap
